{
  "node_id": "node_0",
  "composite_bias_score": 0.4707,
  "content_retention_score": 0.9159,
  "bias_breakdown": {
    "toxicity": 0.0827,
    "sentiment_polarization": 1.0,
    "stereotypes": 1.0,
    "imbalance": 1.0,
    "context_shift": 0.0
  },
  "transformations": [],
  "masked_manifest_len": 0,
  "masked_manifest_preview": [],
  "privacy_manifest_len": 7,
  "privacy_manifest_preview": [
    {
      "token": "<MASK733c7577>",
      "span": [
        1668,
        1680
      ],
      "original": "Contact John",
      "type": "FULL_NAME"
    },
    {
      "token": "<MASK821777eb>",
      "span": [
        1690,
        1710
      ],
      "original": "john.smith@email.com",
      "type": "EMAIL"
    },
    {
      "token": "<MASK885629a4>",
      "span": [
        1719,
        1731
      ],
      "original": "555-123-4567",
      "type": "PHONE"
    },
    {
      "token": "<MASK70f8b4c0>",
      "span": [
        1774,
        1789
      ],
      "original": "123 <MASKcddd99",
      "type": "ADDRESS"
    },
    {
      "token": "<MASKcddd9946>",
      "span": [
        1778,
        1789
      ],
      "original": "Main Street",
      "type": "FULL_NAME"
    }
  ],
  "text_preview": "\n    This disgusting article was written by complete idiots and morons who don't understand anything.\n        Women are naturally inferior at mathematics, science, and logical reasoning because their ...",
  "graph_stats": {
    "total_nodes": 1,
    "total_edges": 0
  }
}